kalc/interactive.py
kalc/misc/cli_optimize.py
kalc/misc/client_config.py
kalc/misc/cluster_dump.py
kalc/misc/const.py
kalc/misc/kind_filter.py
kalc/misc/math.py
kalc/misc/metrics.py
kalc/misc/object_factory.py
kalc/misc/problem.py
kalc/misc/script_generator.py
kalc/misc/selector.py
kalc/misc/support_check.py
kalc/misc/util.py
kalc/model/full.py
kalc/model/kinds/DaemonSet.py
kalc/model/kinds/Deployment.py
kalc/model/kinds/LoadBalancer.py
kalc/model/kinds/Namespace.py
kalc/model/kinds/Node.py
kalc/model/kinds/Pod.py
kalc/model/kinds/PriorityClass.py
kalc/model/kinds/ReplicaSet.py
kalc/model/kinds/Service.py
kalc/model/kubeactions.py
kalc/model/kubernetes.py
kalc/model/labelactions.py
kalc/model/search.py
kalc/model/system/Controller.py
kalc/model/system/NameSpace.py
kalc/model/system/Scheduler.py
kalc/model/system/base.py
kalc/model/system/globals.py
kalc/model/system/primitives.py
kalc/policies/rebalancing.py
kalc/policies/self_antiaffinity.py
kalc/policies/stub.py
kalc/policy.py
kalc-0.1.5.dist-info/entry_points.txt
kalc-0.1.5.dist-info/LICENSE.txt
kalc-0.1.5.dist-info/WHEEL
kalc-0.1.5.dist-info/METADATA
kalc-0.1.5.dist-info/RECORD
