Metadata-Version: 2.1
Name: kalc
Version: 0.1.5
Summary: Kalc - the Kubernetes Calculator core
License: Apache-2.0
Author: CriticalHop Team
Author-email: info@criticalhop.com
Requires-Python: >=3.7
Classifier: License :: OSI Approved :: Apache Software License
Classifier: Programming Language :: Python :: 3
Classifier: Programming Language :: Python :: 3.7
Classifier: Programming Language :: Python :: 3.8
Requires-Dist: PyYAML (>=5.1.2,<6.0.0)
Requires-Dist: Pygments (>=2.5,<3.0)
Requires-Dist: jsonpatch (>=1.24,<2.0)
Requires-Dist: libkubeselector (>=0.0.2,<0.0.3)
Requires-Dist: logzero (>=1.5.0,<2.0.0)
Requires-Dist: pandas (>=0.25.3,<0.26.0)
Requires-Dist: poodle (>=0.2.9,<0.3.0)
Requires-Dist: pytest (>=5.3.5,<6.0.0)
Requires-Dist: setuptools (>=45.0.0,<46.0.0)
